requirements.txt
setup.py
django_listview_queryset/__init__.py
django_listview_queryset.egg-info/PKG-INFO
django_listview_queryset.egg-info/SOURCES.txt
django_listview_queryset.egg-info/dependency_links.txt
django_listview_queryset.egg-info/requires.txt
django_listview_queryset.egg-info/top_level.txt