Metadata-Version: 2.1
Name: django-listview-queryset
Version: 2020.7.1
Summary: ListView QuerySet with custom `count()`
Home-page: https://github.com/andrewp-as-is/django-listview-queryset.py
License: Unlicense
Keywords: django listview queryset
Platform: UNKNOWN
Classifier: Framework :: Django
Classifier: License :: Public Domain
Classifier: Operating System :: OS Independent
Classifier: Programming Language :: Python :: 3
